plasma_properties/__init__.py
plasma_properties/error.py
plasma_properties/parameters.py
plasma_properties/transport.py
plasma_properties/zbar.py
plasma_properties_package-0.1.0.dist-info/LICENSE
plasma_properties_package-0.1.0.dist-info/METADATA
plasma_properties_package-0.1.0.dist-info/WHEEL
plasma_properties_package-0.1.0.dist-info/top_level.txt
plasma_properties_package-0.1.0.dist-info/RECORD
