Metadata-Version: 2.1
Name: plasma-properties-package
Version: 0.1.0
Summary: Compute Plasma Properties
Home-page: https://github.com/lukestanek/plasma_properties
Author: Lucas J. Stanek
Author-email: staneklu@msu.edu
License: UNKNOWN
Platform: UNKNOWN
Classifier: Programming Language :: Python :: 3
Classifier: License :: OSI Approved :: MIT License
Classifier: Operating System :: OS Independent
Requires-Python: >=3.6
